{
  "2012": {
    "USD": 562663.0
  },
  "2013": {
    "USD": 2322372.0
  },
  "2014": {
    "USD": 3425248.0
  },
  "2015": {
    "USD": 4067680.0
  },
  "2016": {
    "USD": 13259035.0
  },
  "2017": {
    "USD": 23397819.0
  },
  "2018": {
    "USD": 24587635.0
  },
  "2019": {
    "USD": 34170359.0
  },
  "2020": {
    "USD": 33874528.0
  },
  "2021": {
    "USD": 62551646.0
  },
  "2022": {
    "USD": 63634048.0
  },
  "2023": {
    "USD": 1622310.0
  },
  "2024": {
    "USD": 857538.0
  },
  "2025": {
    "USD": 662767.0
  },
  "2026": {
    "USD": 402467.0
  }
}