{
  "activity-date": 1498,
  "activity-status": 1498,
  "activity-website": 1498,
  "aid_type": 1498,
  "budget": 1452,
  "budget_not_provided": 0,
  "capital-spend": 0,
  "conditions_attached": 0,
  "contact-info": 1498,
  "country_or_region": 1498,
  "description": 1498,
  "document-link": 1498,
  "iati-identifier": 1498,
  "location": 276,
  "location_point_pos": 276,
  "participating-org": 1498,
  "recipient_language": 347,
  "reporting-org": 1498,
  "result_indicator": 1477,
  "sector": 1498,
  "sector_dac": 1498,
  "title": 1498,
  "transaction_commitment": 0,
  "transaction_currency": 1402,
  "transaction_spend": 960,
  "transaction_traceability": 1183,
  "version": 1498
}