{
  "2": {
    ".//@default-currency": {
      "uncdf-activities.xml": {
        "USD": 271
      }
    },
    ".//activity-date/@type": {
      "uncdf-activities.xml": {
        "1": 267,
        "3": 271,
        "2": 4
      }
    },
    ".//activity-status/@code": {
      "uncdf-activities.xml": {
        "2": 251,
        "4": 1,
        "3": 19
      }
    },
    ".//budget/@status": {
      "uncdf-activities.xml": {
        "2": 532,
        "1": 85
      }
    },
    ".//budget/@type": {
      "uncdf-activities.xml": {
        "1": 561
      }
    },
    ".//budget/value/@currency": {
      "uncdf-activities.xml": {
        "USD": 540
      }
    },
    ".//contact-info/@type": {
      "uncdf-activities.xml": {
        "1": 3
      }
    },
    ".//description/@type": {
      "uncdf-activities.xml": {
        "1": 271
      }
    },
    ".//document-link/@format": {
      "uncdf-activities.xml": {
        "application/pdf": 38,
        "application/http": 6,
        "application/vnd.dtg.local.html": 26
      }
    },
    ".//document-link/category/@code": {
      "uncdf-activities.xml": {
        "A07": 17,
        "A02": 23,
        "A08": 15,
        "B01": 15
      }
    },
    ".//document-link/language/@code": {
      "uncdf-activities.xml": {
        "en": 68,
        "fr": 2
      }
    },
    ".//other-identifier/@type": {
      "uncdf-activities.xml": {
        "B1": 251,
        "A9": 1
      }
    },
    ".//participating-org/@role": {
      "uncdf-activities.xml": {
        "1": 278
      }
    },
    ".//participating-org/@type": {
      "uncdf-activities.xml": {
        "15": 32,
        "10": 61,
        "40": 160,
        "60": 15,
        "21": 4,
        "70": 4,
        "22": 2
      }
    },
    ".//recipient-country/@code": {
      "uncdf-activities.xml": {
        "CD": 19,
        "BJ": 16,
        "LA": 35,
        "LR": 7,
        "MW": 21,
        "NP": 39,
        "SN": 31,
        "UG": 36,
        "ZM": 11,
        "US": 57,
        "BW": 7,
        "KH": 33,
        "LS": 11,
        "MZ": 24,
        "MM": 30,
        "SZ": 7,
        "ZW": 9,
        "BD": 28,
        "ET": 20,
        "BF": 22,
        "BI": 7,
        "CM": 3,
        "GH": 12,
        "RW": 11,
        "TZ": 31,
        "ML": 16,
        "NE": 24,
        "CI": 3,
        "GW": 2,
        "TG": 9,
        "SO": 5,
        "VN": 8,
        "BT": 7,
        "TV": 6,
        "FJ": 6,
        "PG": 7,
        "SB": 6,
        "VU": 5,
        "TO": 5,
        "WS": 6,
        "MG": 3,
        "GN": 9,
        "MY": 1,
        "CN": 1,
        "JO": 1,
        "ID": 2,
        "GM": 7,
        "TL": 1,
        "TH": 6,
        "ZA": 1,
        "SL": 1,
        "FR": 1,
        "PE": 1
      }
    },
    ".//reporting-org/@type": {
      "uncdf-activities.xml": {
        "40": 271
      }
    },
    ".//sector[@vocabulary = '1' or not(@vocabulary)]/@code": {
      "uncdf-activities.xml": {
        "15111": 171,
        "15128": 100,
        "24030": 2,
        "24010": 4,
        "12240": 1
      }
    },
    ".//sector[@vocabulary = '7']/@code": {
      "uncdf-activities.xml": {
        "7": 1
      }
    },
    ".//sector[@vocabulary = '8']/@code": {
      "uncdf-activities.xml": {
        "1.4": 71,
        "17.3": 15,
        "13.b": 19,
        "7.1": 11,
        "11.1": 7,
        "1.2": 4,
        "8.4": 13,
        "8.10": 6,
        "2.1": 2,
        "5.a": 4,
        "1.a": 5,
        "17.9": 2,
        "6.5": 1,
        "10.c": 2,
        "2.2": 1
      }
    },
    ".//sector/@vocabulary": {
      "uncdf-activities.xml": {
        "1": 278,
        "8": 163,
        "7": 1
      }
    },
    ".//transaction/aid-type[@vocabulary = '1' or not(@vocabulary)]/@code": {
      "uncdf-activities.xml": {
        "B01": 155,
        "B03": 5,
        "C01": 144,
        "A02": 31,
        "B02": 8,
        "E01": 2,
        "D02": 1
      }
    },
    ".//transaction/aid-type/@vocabulary": {
      "uncdf-activities.xml": {
        "1": 346
      }
    },
    ".//transaction/finance-type/@code": {
      "uncdf-activities.xml": {
        "110": 49
      }
    },
    ".//transaction/provider-org/@type": {
      "uncdf-activities.xml": {
        "40": 401
      }
    },
    ".//transaction/transaction-type/@code": {
      "uncdf-activities.xml": {
        "4": 650
      }
    },
    ".//transaction/value/@currency": {
      "uncdf-activities.xml": {
        "USD": 76
      }
    },
    ".//@xml:lang": {
      "uncdf-activities.xml": {
        "en": 613,
        "fr": 10
      }
    }
  }
}