{
  "2011": {
    "USD": 2354857.0
  },
  "2012": {
    "USD": 16559640.5
  },
  "2013": {
    "USD": 32692271.5
  },
  "2014": {
    "USD": 16878037.5
  },
  "2015": {
    "USD": 16279334.5
  },
  "2016": {
    "USD": 14405053.0
  },
  "2017": {
    "USD": 15789188.5
  },
  "2018": {
    "USD": 15994656.0
  },
  "2019": {
    "USD": 13089153.5
  },
  "2020": {
    "USD": 11582805.5
  },
  "2021": {
    "USD": 18549778.0
  },
  "2022": {
    "USD": 22237306.0
  },
  "2023": {
    "USD": 15013161.5
  },
  "2024": {
    "USD": 10997031.0
  }
}