{
  "activity-date": 4025,
  "activity-status": 4025,
  "activity-website": 0,
  "aid_type": 4025,
  "budget": 1802,
  "budget_not_provided": 0,
  "capital-spend": 0,
  "conditions_attached": 0,
  "contact-info": 3997,
  "country_or_region": 3686,
  "description": 2957,
  "document-link": 0,
  "iati-identifier": 4025,
  "location": 0,
  "location_point_pos": 0,
  "participating-org": 4025,
  "recipient_language": 495,
  "reporting-org": 4025,
  "result_indicator": 662,
  "sector": 3929,
  "sector_dac": 3929,
  "title": 2931,
  "transaction_commitment": 1508,
  "transaction_currency": 2334,
  "transaction_spend": 1963,
  "transaction_traceability": 4025,
  "version": 4025
}