{
  "1": {
    "USD": {
      "wbtf-tf072854.xml": {
        "2020": 3788645.0
      },
      "wbtf-tf071070.xml": {
        "2008": 25000000.0,
        "2009": 2500000.0
      },
      "wbtf-tf072305.xml": {
        "2016": 5000000.0
      },
      "wbtf-tf072567.xml": {
        "2018": 4670000.0,
        "2017": 4366500.0
      },
      "wbtf-tf073069.xml": {
        "2018": 12000000.0
      },
      "wbtf-tf071624.xml": {
        "2020": 310524.04,
        "2019": 55414.23,
        "2021": 1401685.92
      },
      "wbtf-tf072102.xml": {
        "2014": 22940475.86,
        "2016": 12254749.51
      }
    }
  }
}